{
  "kind": "collectionType",
  "collectionName": "nfc_passes",
  "info": {
    "singularName": "nfc-pass",
    "pluralName": "nfc-passes",
    "displayName": "NfcPass",
    "description": ""
  },
  "options": {
    "draftAndPublish": false
  },
  "pluginOptions": {},
  "attributes": {
    "deviceId": {
      "type": "string",
      "required": true,
      "unique": false
    },
    "studentId": {
      "type": "string",
      "required": true
    },
    "connected": {
      "type": "boolean",
      "default": false,
      "required": true
    },
    "deviceName": {
      "type": "string",
      "required": true
    },
    "code": {
      "type": "string",
      "required": true,
      "unique": false
    }
  }
}
